syzoj_tools-0.2.1.data/purelib/syzoj_tools/__init__.py
syzoj_tools-0.2.1.data/purelib/syzoj_tools/contest.py
syzoj_tools-0.2.1.data/purelib/syzoj_tools/problem.py
syzoj_tools-0.2.1.data/purelib/syzoj_tools/checkers/__init__.py
syzoj_tools-0.2.1.data/purelib/syzoj_tools/checkers/acmp
syzoj_tools-0.2.1.data/purelib/syzoj_tools/checkers/acmp.cpp
syzoj_tools-0.2.1.data/purelib/syzoj_tools/checkers/builtin.py
syzoj_tools-0.2.1.data/purelib/syzoj_tools/checkers/caseicmp
syzoj_tools-0.2.1.data/purelib/syzoj_tools/checkers/caseicmp.cpp
syzoj_tools-0.2.1.data/purelib/syzoj_tools/checkers/casencmp
syzoj_tools-0.2.1.data/purelib/syzoj_tools/checkers/casencmp.cpp
syzoj_tools-0.2.1.data/purelib/syzoj_tools/checkers/casewcmp
syzoj_tools-0.2.1.data/purelib/syzoj_tools/checkers/casewcmp.cpp
syzoj_tools-0.2.1.data/purelib/syzoj_tools/checkers/cena.py
syzoj_tools-0.2.1.data/purelib/syzoj_tools/checkers/dcmp
syzoj_tools-0.2.1.data/purelib/syzoj_tools/checkers/dcmp.cpp
syzoj_tools-0.2.1.data/purelib/syzoj_tools/checkers/fcmp
syzoj_tools-0.2.1.data/purelib/syzoj_tools/checkers/fcmp.cpp
syzoj_tools-0.2.1.data/purelib/syzoj_tools/checkers/hcmp
syzoj_tools-0.2.1.data/purelib/syzoj_tools/checkers/hcmp.cpp
syzoj_tools-0.2.1.data/purelib/syzoj_tools/checkers/icmp
syzoj_tools-0.2.1.data/purelib/syzoj_tools/checkers/icmp.cpp
syzoj_tools-0.2.1.data/purelib/syzoj_tools/checkers/lcmp
syzoj_tools-0.2.1.data/purelib/syzoj_tools/checkers/lcmp.cpp
syzoj_tools-0.2.1.data/purelib/syzoj_tools/checkers/lemon.py
syzoj_tools-0.2.1.data/purelib/syzoj_tools/checkers/loj.py
syzoj_tools-0.2.1.data/purelib/syzoj_tools/checkers/ncmp
syzoj_tools-0.2.1.data/purelib/syzoj_tools/checkers/ncmp.cpp
syzoj_tools-0.2.1.data/purelib/syzoj_tools/checkers/pointscmp
syzoj_tools-0.2.1.data/purelib/syzoj_tools/checkers/pointscmp.cpp
syzoj_tools-0.2.1.data/purelib/syzoj_tools/checkers/rcmp
syzoj_tools-0.2.1.data/purelib/syzoj_tools/checkers/rcmp.cpp
syzoj_tools-0.2.1.dist-info/METADATA
syzoj_tools-0.2.1.dist-info/RECORD
syzoj_tools-0.2.1.dist-info/WHEEL
syzoj_tools-0.2.1.dist-info/entry_points.txt
syzoj_tools-0.2.1.dist-info/top_level.txt
