Metadata-Version: 2.1
Name: syzoj-tools
Version: 0.2.1
Summary: The SYZOJ tools
Home-page: http://github.com/syzoj/syzoj-tools
Author: vincent163
Author-email: 479258741@qq.com
License: UNKNOWN
Platform: UNKNOWN
Classifier: Development Status :: 2 - Pre-Alpha
Classifier: Environment :: Console
Classifier: License :: OSI Approved :: MIT License
Classifier: Operating System :: POSIX
Classifier: Programming Language :: Python :: 3 :: Only
Requires-Python: >=3.5
Requires-Dist: ruamel.yaml
